[{"IdName":"Fireball","AbilityType":"SPELL","AbilityShotType":"PROJECTILE","AttacksPerSec":1.0,"TargetRange":4.0,"BaseCritical":4.0,"TargetType":0,"ProjectileSpeed":5.0,"ProjectileSize":1.0,"ProjectileCount":1,"ProjectileSpread":90,"DoesProjectileSpread":true,"AreaRadius":0.0,"AreaLength":0.0,"HitscanDelay":0.0,"WeaponMultiplier":0.0,"WeaponMultiplierScaling":0.0,"DamageLevels":{"FIRE":{"Damage":[{"Min":8,"Max":13},{"Min":11,"Max":16},{"Min":13,"Max":20},{"Min":16,"Max":24},{"Min":20,"Max":29},{"Min":23,"Max":35},{"Min":27,"Max":41},{"Min":32,"Max":48},{"Min":37,"Max":55},{"Min":42,"Max":63},{"Min":48,"Max":72},{"Min":55,"Max":82},{"Min":62,"Max":94},{"Min":71,"Max":106},{"Min":79,"Max":119},{"Min":89,"Max":134},{"Min":100,"Max":150},{"Min":112,"Max":168},{"Min":125,"Max":187},{"Min":139,"Max":209},{"Min":155,"Max":232},{"Min":171,"Max":257},{"Min":190,"Max":285},{"Min":210,"Max":315},{"Min":232,"Max":348},{"Min":256,"Max":384},{"Min":282,"Max":423},{"Min":311,"Max":466},{"Min":342,"Max":512},{"Min":375,"Max":563},{"Min":412,"Max":618},{"Min":452,"Max":677},{"Min":495,"Max":742},{"Min":541,"Max":812},{"Min":592,"Max":888},{"Min":647,"Max":971},{"Min":707,"Max":1061},{"Min":772,"Max":1158},{"Min":842,"Max":1263},{"Min":918,"Max":1377},{"Min":1000,"Max":1501},{"Min":1089,"Max":1634},{"Min":1186,"Max":1779},{"Min":1290,"Max":1935},{"Min":1403,"Max":2104},{"Min":1525,"Max":2287},{"Min":1657,"Max":2485},{"Min":1799,"Max":2699},{"Min":1953,"Max":2929},{"Min":2119,"Max":3179},{"Min":2299,"Max":3448},{"Min":2492,"Max":3739},{"Min":2702,"Max":4052},{"Min":2927,"Max":4391},{"Min":3171,"Max":4756},{"Min":3433,"Max":5150},{"Min":3717,"Max":5575},{"Min":4022,"Max":6033},{"Min":4352,"Max":6527},{"Min":4707,"Max":7060},{"Min":5089,"Max":7634},{"Min":5501,"Max":8252},{"Min":5946,"Max":8918},{"Min":6424,"Max":9636},{"Min":6939,"Max":10409}],"MinMult":0.799999952,"MaxMult":1.2}},"FlatDamageMultiplier":1.0,"BaseAbilityPower":1.5,"AbilityScaling":1.042,"GroupTypes":[],"WeaponRestrictions":[],"BonusProperties":[{"bonusType":"BURN_CHANCE","modifyType":"FLAT_ADDITION","initialValue":10.0,"growthValue":0.2},{"bonusType":"BURN_EFFECTIVENESS","modifyType":"MULTIPLY","initialValue":-50.0,"growthValue":0.3}],"EffectSprite":"","LinkedAbility":{"inheritsDamage":true,"inheritDamagePercent":0.5,"inheritDamagePercentScaling":0.002,"AbilityId":"Fireball_Link","Type":"ON_HIT","Time":0.0,"InheritsDamage":true,"InheritDamagePercent":0.5,"InheritDamagePercentScaling":0.002},"AppliedEffects":[],"HasLinkedAbility":true,"UseWeaponRange":false},{"IdName":"IceNeedles","AbilityType":"SPELL","AbilityShotType":"PROJECTILE","AttacksPerSec":1.0,"TargetRange":3.50000048,"BaseCritical":4.0,"TargetType":0,"ProjectileSpeed":8.0,"ProjectileSize":0.8,"ProjectileCount":3,"ProjectileSpread":9,"DoesProjectileSpread":false,"AreaRadius":0.0,"AreaLength":0.0,"HitscanDelay":0.0,"WeaponMultiplier":0.0,"WeaponMultiplierScaling":0.0,"DamageLevels":{"COLD":{"Damage":[{"Min":7,"Max":10},{"Min":8,"Max":11},{"Min":9,"Max":14},{"Min":11,"Max":16},{"Min":13,"Max":18},{"Min":15,"Max":21},{"Min":17,"Max":24},{"Min":19,"Max":28},{"Min":22,"Max":32},{"Min":25,"Max":36},{"Min":28,"Max":40},{"Min":32,"Max":45},{"Min":36,"Max":51},{"Min":40,"Max":57},{"Min":44,"Max":63},{"Min":49,"Max":71},{"Min":55,"Max":78},{"Min":61,"Max":87},{"Min":67,"Max":96},{"Min":74,"Max":106},{"Min":82,"Max":117},{"Min":91,"Max":129},{"Min":100,"Max":142},{"Min":110,"Max":156},{"Min":120,"Max":172},{"Min":132,"Max":188},{"Min":144,"Max":206},{"Min":158,"Max":226},{"Min":173,"Max":247},{"Min":189,"Max":270},{"Min":206,"Max":295},{"Min":225,"Max":321},{"Min":245,"Max":350},{"Min":267,"Max":381},{"Min":291,"Max":415},{"Min":316,"Max":451},{"Min":343,"Max":491},{"Min":373,"Max":533},{"Min":405,"Max":579},{"Min":440,"Max":628},{"Min":477,"Max":681},{"Min":517,"Max":738},{"Min":560,"Max":800},{"Min":606,"Max":866},{"Min":656,"Max":937},{"Min":710,"Max":1014},{"Min":768,"Max":1097},{"Min":830,"Max":1185},{"Min":897,"Max":1281},{"Min":969,"Max":1384},{"Min":1046,"Max":1494},{"Min":1129,"Max":1613},{"Min":1218,"Max":1740},{"Min":1314,"Max":1877},{"Min":1417,"Max":2024},{"Min":1528,"Max":2182},{"Min":1646,"Max":2352},{"Min":1774,"Max":2534},{"Min":1910,"Max":2729},{"Min":2057,"Max":2939},{"Min":2215,"Max":3164},{"Min":2383,"Max":3405},{"Min":2565,"Max":3664},{"Min":2759,"Max":3941},{"Min":2967,"Max":4238}],"MinMult":0.6999999,"MaxMult":1.0}},"FlatDamageMultiplier":0.25,"BaseAbilityPower":0.97,"AbilityScaling":1.03899992,"GroupTypes":[],"WeaponRestrictions":[],"BonusProperties":[],"EffectSprite":"","LinkedAbility":{"inheritsDamage":false,"inheritDamagePercent":0.0,"inheritDamagePercentScaling":0.0,"AbilityId":null,"Type":"ON_HIT","Time":0.0,"InheritsDamage":false,"InheritDamagePercent":0.0,"InheritDamagePercentScaling":0.0},"AppliedEffects":[],"HasLinkedAbility":false,"UseWeaponRange":false},{"IdName":"Cleave","AbilityType":"ATTACK","AbilityShotType":"ARC_AOE","AttacksPerSec":1.0,"TargetRange":1.0,"BaseCritical":0.0,"TargetType":0,"ProjectileSpeed":1.0,"ProjectileSize":1.0,"ProjectileCount":1,"ProjectileSpread":120,"DoesProjectileSpread":false,"AreaRadius":1.0,"AreaLength":1.0,"HitscanDelay":0.0,"WeaponMultiplier":1.0,"WeaponMultiplierScaling":0.01,"DamageLevels":{},"FlatDamageMultiplier":1.0,"BaseAbilityPower":1.41000009,"AbilityScaling":1.042,"GroupTypes":["MELEE_ATTACK"],"WeaponRestrictions":["MELEE_WEAPON"],"BonusProperties":[],"EffectSprite":"","LinkedAbility":{"inheritsDamage":false,"inheritDamagePercent":0.0,"inheritDamagePercentScaling":0.0,"AbilityId":null,"Type":"ON_HIT","Time":0.0,"InheritsDamage":false,"InheritDamagePercent":0.0,"InheritDamagePercentScaling":0.0},"AppliedEffects":[],"HasLinkedAbility":false,"UseWeaponRange":true},{"IdName":"Fireball_Link","AbilityType":"SPELL","AbilityShotType":"NOVA_AOE","AttacksPerSec":0.0,"TargetRange":3.0,"BaseCritical":4.0,"TargetType":0,"ProjectileSpeed":5.0,"ProjectileSize":1.0,"ProjectileCount":1,"ProjectileSpread":45,"DoesProjectileSpread":false,"AreaRadius":1.0,"AreaLength":0.0,"HitscanDelay":0.0,"WeaponMultiplier":0.0,"WeaponMultiplierScaling":0.0,"DamageLevels":{},"FlatDamageMultiplier":1.0,"BaseAbilityPower":1.5,"AbilityScaling":1.042,"GroupTypes":[],"WeaponRestrictions":[],"BonusProperties":[],"EffectSprite":"","LinkedAbility":{"inheritsDamage":true,"inheritDamagePercent":0.1,"inheritDamagePercentScaling":0.01,"AbilityId":"Fireball","Type":"TIME","Time":0.01,"InheritsDamage":true,"InheritDamagePercent":0.1,"InheritDamagePercentScaling":0.01},"AppliedEffects":[],"HasLinkedAbility":false,"UseWeaponRange":false}]