{
  "prefix": {
    "NO_GROUP": [
      "Grim",
      "Cursed",
      "Chaos",
      "Heavensent",
      "Hell",
      "Deadly",
      "Gorgon's",
      "Vile",
      "Joyous",
      "Arcane",
      "Scrying",
      "Reflecting",
      "Death",
      "Melancholy",
      "Runic",
      "Doom",
      "Dread",
      "Raven",
      "Pillaging",
      "Oathbreaker's",
      "Sinner's",
      "Torture",
      "Deadly",
      "Malignant",
      "Waking",
      "Abyssal",
      "Visceral",
      "Gloom",
      "Demonic",
      "Angelic",
      "Living",
      "Ancient",
      "Primal",
      "Renowned",
      "Kraken's",
      "Notorious",
      "Winged",
      "Saint's",
      "Inquisitor's",
      "Hellbound",
      "Heavenly",
      "Cherubim's",
      "Magnificent",
      "Blood",
      "Plague",
      "Scouring",
      "Exalted",
      "Spirited",
      "Silent",
      "Feared",
      "Anger",
      "Mystic",
      "Draconic",
      "Gilded",
      "Primed",
      "Cryptic",
      "Tempered",
      "Transient",
      "Ethereal",
      "Gazing",
      "Solemn",
      "Peculiar",
      "Nightmare",
      "Dream",
      "Derelict"
    ]

  },
  "suffix": {
    "NO_GROUP": [
      "Squire",
      "Pawn",
      "Star",
      "Bile",
      "Guidance",
      "Tempest",
      "Shard",
      "Retribution",
      "Rise",
      "Knell",
      "Augur"
    ],
    "WEAPON": [
      "Bane",
      "Crasher",
      "Slayer",
      "Striker",
      "Armament",
      "Gale",
      "Vortex",
      "Killer",
      "Siphon"
    ],
    "ALL_ARMOR": [
      "Protector",
      "Expanse",
      "Watch",
      "Ward",
      "Curtain",
      "Scale",
      "Hide",
      "Shelter",
      "Shell"
    ],
    "BODY_ARMOR": [
      "Sanctuary",
      "Shroud",
      "Enclosure",
      "Suit",
      "Coat"
    ],
    "SHIELD": [
      "Aegis",
      "Keep",
      "Castle",
      "Fortress"
    ],
    "ALL_ACCESSORY": [
      "Secret",
      "Gear",
      "Charm",
      "Trinket",
      "Loop",
      "Gyre",
      "Spiral"
    ],
    "RING": [
      "Whorl",
      "Band",
      "Coil",
      "Hoop",
      "Halo"
    ]
  }
}